deal_solver/__init__.py
deal_solver/_annotations.py
deal_solver/_ast.py
deal_solver/_cached_property.py
deal_solver/_eval_contracts.py
deal_solver/_eval_expr.py
deal_solver/_eval_stmt.py
deal_solver/_exceptions.py
deal_solver/_goal.py
deal_solver/_model.py
deal_solver/_registry.py
deal_solver/_theorem.py
deal_solver/_types.py
deal_solver/py.typed
deal_solver/_context/__init__.py
deal_solver/_context/_context.py
deal_solver/_context/_layer.py
deal_solver/_context/_scope.py
deal_solver/_context/_trace.py
deal_solver/_funcs/__init__.py
deal_solver/_funcs/_builtins.py
deal_solver/_funcs/_math.py
deal_solver/_funcs/_os_path.py
deal_solver/_funcs/_random.py
deal_solver/_funcs/_re.py
deal_solver/_funcs/_registry.py
deal_solver/_proxies/__init__.py
deal_solver/_proxies/_bool.py
deal_solver/_proxies/_dict.py
deal_solver/_proxies/_float.py
deal_solver/_proxies/_func.py
deal_solver/_proxies/_funcs.py
deal_solver/_proxies/_int.py
deal_solver/_proxies/_lambda.py
deal_solver/_proxies/_list.py
deal_solver/_proxies/_method.py
deal_solver/_proxies/_methods.py
deal_solver/_proxies/_pattern.py
deal_solver/_proxies/_proxy.py
deal_solver/_proxies/_registry.py
deal_solver/_proxies/_set.py
deal_solver/_proxies/_str.py
deal_solver/_proxies/_type_factory.py
deal_solver/_proxies/_var_tuple.py
deal_solver-0.1.2.dist-info/LICENSE
deal_solver-0.1.2.dist-info/WHEEL
deal_solver-0.1.2.dist-info/METADATA
deal_solver-0.1.2.dist-info/RECORD
