Metadata-Version: 2.1
Name: deal-solver
Version: 0.1.2
Summary: z3-powered solver (theorem prover) for deal.
Home-page: https://github.com/life4/deal-solver
License: MIT
Keywords: deal,contracts,verification
Author: Gram
Author-email: gram@orsinium.dev
Requires-Python: >=3.7
Classifier: Development Status :: 5 - Production/Stable
Classifier: Environment :: Plugins
Classifier: Intended Audience :: Developers
Classifier: License :: OSI Approved :: MIT License
Classifier: Programming Language :: Python
Classifier: Topic :: Software Development
Classifier: Topic :: Software Development :: Libraries :: Python Modules
Classifier: Topic :: Software Development :: Quality Assurance
Requires-Dist: astroid
Requires-Dist: z3-solver
Requires-Dist: flake8 ; extra == "lint"
Requires-Dist: flake8-bugbear ; extra == "lint"
Requires-Dist: flake8-commas ; extra == "lint"
Requires-Dist: flake8-quotes ; extra == "lint"
Requires-Dist: isort ; extra == "lint"
Requires-Dist: unify ; extra == "lint"
Requires-Dist: mypy>=0.910 ; extra == "lint"
Requires-Dist: hypothesis ; extra == "test"
Requires-Dist: pytest ; extra == "test"
Requires-Dist: pytest-cov ; extra == "test"
Requires-Dist: pytest-xdist ; extra == "test"
Provides-Extra: lint
Provides-Extra: test
